{"v":4,"entries":{"configure-your-project--docs":{"id":"configure-your-project--docs","title":"Configure your project","name":"Docs","importPath":"./stories/Configure.mdx","storiesImports":[],"type":"docs","tags":["unattached-mdx","docs"]},"common-twixtalert--docs":{"id":"common-twixtalert--docs","title":"Common/TwixtAlert","name":"Docs","importPath":"./stories/Alert.stories.js","type":"docs","tags":["autodocs","docs"],"storiesImports":[]},"common-twixtalert--announcement":{"type":"story","id":"common-twixtalert--announcement","name":"Announcement","title":"Common/TwixtAlert","importPath":"./stories/Alert.stories.js","tags":["autodocs","story"]},"common-twixtalert--error-notice":{"type":"story","id":"common-twixtalert--error-notice","name":"Error Notice","title":"Common/TwixtAlert","importPath":"./stories/Alert.stories.js","tags":["autodocs","story"]},"common-twixtalert--notification":{"type":"story","id":"common-twixtalert--notification","name":"Notification","title":"Common/TwixtAlert","importPath":"./stories/Alert.stories.js","tags":["autodocs","story"]},"common-twixtalert--increase-padding":{"type":"story","id":"common-twixtalert--increase-padding","name":"Increase Padding","title":"Common/TwixtAlert","importPath":"./stories/Alert.stories.js","tags":["autodocs","story"]},"common-twixtalert--background-change":{"type":"story","id":"common-twixtalert--background-change","name":"Background Change","title":"Common/TwixtAlert","importPath":"./stories/Alert.stories.js","tags":["autodocs","story"]},"common-twixtalert--border-color-change":{"type":"story","id":"common-twixtalert--border-color-change","name":"Border Color Change","title":"Common/TwixtAlert","importPath":"./stories/Alert.stories.js","tags":["autodocs","story"]},"common-twixtalert--text-color-change":{"type":"story","id":"common-twixtalert--text-color-change","name":"Text Color Change","title":"Common/TwixtAlert","importPath":"./stories/Alert.stories.js","tags":["autodocs","story"]},"common-twixtbutton--docs":{"id":"common-twixtbutton--docs","title":"Common/TwixtButton","name":"Docs","importPath":"./stories/Button.stories.js","type":"docs","tags":["autodocs","docs"],"storiesImports":[]},"common-twixtbutton--click-button":{"type":"story","id":"common-twixtbutton--click-button","name":"Click Button","title":"Common/TwixtButton","importPath":"./stories/Button.stories.js","tags":["autodocs","story"]},"common-twixtcheckbox--docs":{"id":"common-twixtcheckbox--docs","title":"Common/TwixtCheckbox","name":"Docs","importPath":"./stories/Checkbox.stories.js","type":"docs","tags":["autodocs","docs"],"storiesImports":[]},"common-twixtcheckbox--check-button":{"type":"story","id":"common-twixtcheckbox--check-button","name":"Check Button","title":"Common/TwixtCheckbox","importPath":"./stories/Checkbox.stories.js","tags":["autodocs","story"]},"common-commentssystem--docs":{"id":"common-commentssystem--docs","title":"Common/CommentsSystem","name":"Docs","importPath":"./stories/Comments.stories.js","type":"docs","tags":["autodocs","docs"],"storiesImports":[]},"common-commentssystem--comment-box":{"type":"story","id":"common-commentssystem--comment-box","name":"Comment Box","title":"Common/CommentsSystem","importPath":"./stories/Comments.stories.js","tags":["autodocs","story"]},"common-twixtcopybutton--docs":{"id":"common-twixtcopybutton--docs","title":"Common/TwixtCopyButton","name":"Docs","importPath":"./stories/CopyButton.stories.js","type":"docs","tags":["autodocs","docs"],"storiesImports":[]},"common-twixtcopybutton--copy-props":{"type":"story","id":"common-twixtcopybutton--copy-props","name":"Copy Props","title":"Common/TwixtCopyButton","importPath":"./stories/CopyButton.stories.js","tags":["autodocs","story"]},"common-twixtdialog--docs":{"id":"common-twixtdialog--docs","title":"Common/TwixtDialog","name":"Docs","importPath":"./stories/Dialog.stories.js","type":"docs","tags":["autodocs","docs"],"storiesImports":[]},"common-twixtdialog--dialog-box":{"type":"story","id":"common-twixtdialog--dialog-box","name":"Dialog Box","title":"Common/TwixtDialog","importPath":"./stories/Dialog.stories.js","tags":["autodocs","story"]},"common-twixtheader--docs":{"id":"common-twixtheader--docs","title":"Common/TwixtHeader","name":"Docs","importPath":"./stories/Header.stories.js","type":"docs","tags":["autodocs","docs"],"storiesImports":[]},"common-twixtheader--default":{"type":"story","id":"common-twixtheader--default","name":"Default","title":"Common/TwixtHeader","importPath":"./stories/Header.stories.js","tags":["autodocs","story"]},"common-twixtheading--docs":{"id":"common-twixtheading--docs","title":"Common/TwixtHeading","name":"Docs","importPath":"./stories/Heading.stories.js","type":"docs","tags":["autodocs","docs"],"storiesImports":[]},"common-twixtheading--heading-1":{"type":"story","id":"common-twixtheading--heading-1","name":"Heading 1","title":"Common/TwixtHeading","importPath":"./stories/Heading.stories.js","tags":["autodocs","story"]},"common-twixtheading--heading-2":{"type":"story","id":"common-twixtheading--heading-2","name":"Heading 2","title":"Common/TwixtHeading","importPath":"./stories/Heading.stories.js","tags":["autodocs","story"]},"common-twixtsinglelineinput--docs":{"id":"common-twixtsinglelineinput--docs","title":"Common/TwixtSingleLineInput","name":"Docs","importPath":"./stories/InputSingleLine.stories.js","type":"docs","tags":["autodocs","docs"],"storiesImports":[]},"common-twixtsinglelineinput--welcome":{"type":"story","id":"common-twixtsinglelineinput--welcome","name":"Welcome","title":"Common/TwixtSingleLineInput","importPath":"./stories/InputSingleLine.stories.js","tags":["autodocs","story"]},"common-twixtmodal--docs":{"id":"common-twixtmodal--docs","title":"Common/TwixtModal","name":"Docs","importPath":"./stories/Modal.stories.js","type":"docs","tags":["autodocs","docs"],"storiesImports":[]},"common-twixtmodal--login":{"type":"story","id":"common-twixtmodal--login","name":"Login","title":"Common/TwixtModal","importPath":"./stories/Modal.stories.js","tags":["autodocs","story"]},"common-twixtmodal--error":{"type":"story","id":"common-twixtmodal--error","name":"Error","title":"Common/TwixtModal","importPath":"./stories/Modal.stories.js","tags":["autodocs","story"]},"common-twixtmodal--notification":{"type":"story","id":"common-twixtmodal--notification","name":"Notification","title":"Common/TwixtModal","importPath":"./stories/Modal.stories.js","tags":["autodocs","story"]},"example-page--logged-out":{"type":"story","id":"example-page--logged-out","name":"Logged Out","title":"Example/Page","importPath":"./stories/Page.stories.js","tags":["story"]},"example-page--logged-in":{"type":"story","id":"example-page--logged-in","name":"Logged In","title":"Example/Page","importPath":"./stories/Page.stories.js","tags":["play-fn","story"]},"common-twixtprogressline--docs":{"id":"common-twixtprogressline--docs","title":"Common/TwixtProgressLine","name":"Docs","importPath":"./stories/PageProgressLine.stories.js","type":"docs","tags":["autodocs","docs"],"storiesImports":[]},"common-twixtprogressline--red":{"type":"story","id":"common-twixtprogressline--red","name":"Red","title":"Common/TwixtProgressLine","importPath":"./stories/PageProgressLine.stories.js","tags":["autodocs","story"]},"common-twixtprogressline--yellow":{"type":"story","id":"common-twixtprogressline--yellow","name":"Yellow","title":"Common/TwixtProgressLine","importPath":"./stories/PageProgressLine.stories.js","tags":["autodocs","story"]},"common-twixtprogressline--blue":{"type":"story","id":"common-twixtprogressline--blue","name":"Blue","title":"Common/TwixtProgressLine","importPath":"./stories/PageProgressLine.stories.js","tags":["autodocs","story"]},"common-twixtpostitem--docs":{"id":"common-twixtpostitem--docs","title":"Common/TwixtPostItem","name":"Docs","importPath":"./stories/PostItem.stories.js","type":"docs","tags":["autodocs","docs"],"storiesImports":[]},"common-twixtpostitem--post-one":{"type":"story","id":"common-twixtpostitem--post-one","name":"Post One","title":"Common/TwixtPostItem","importPath":"./stories/PostItem.stories.js","tags":["autodocs","story"]},"common-twixtpostitem--post-two":{"type":"story","id":"common-twixtpostitem--post-two","name":"Post Two","title":"Common/TwixtPostItem","importPath":"./stories/PostItem.stories.js","tags":["autodocs","story"]},"common-twixtcodeeditor--docs":{"id":"common-twixtcodeeditor--docs","title":"Common/TwixtCodeEditor","name":"Docs","importPath":"./stories/SimpleCodeEditor.stories.js","type":"docs","tags":["autodocs","docs"],"storiesImports":[]},"common-twixtcodeeditor--default":{"type":"story","id":"common-twixtcodeeditor--default","name":"Default","title":"Common/TwixtCodeEditor","importPath":"./stories/SimpleCodeEditor.stories.js","tags":["autodocs","story"]},"common-twixtcodeeditor--full-screen":{"type":"story","id":"common-twixtcodeeditor--full-screen","name":"Full Screen","title":"Common/TwixtCodeEditor","importPath":"./stories/SimpleCodeEditor.stories.js","tags":["autodocs","story"]},"common-simpletable--docs":{"id":"common-simpletable--docs","title":"Common/SimpleTable","name":"Docs","importPath":"./stories/SimpleTable.stories.js","type":"docs","tags":["autodocs","docs"],"storiesImports":[]},"common-simpletable--default":{"type":"story","id":"common-simpletable--default","name":"Default","title":"Common/SimpleTable","importPath":"./stories/SimpleTable.stories.js","tags":["autodocs","story"]},"common-simpletable--custom-data":{"type":"story","id":"common-simpletable--custom-data","name":"Custom Data","title":"Common/SimpleTable","importPath":"./stories/SimpleTable.stories.js","tags":["autodocs","story"]},"common-twixtskeleton--docs":{"id":"common-twixtskeleton--docs","title":"Common/TwixtSkeleton","name":"Docs","importPath":"./stories/Skeleton.stories.js","type":"docs","tags":["autodocs","docs"],"storiesImports":[]},"common-twixtskeleton--left-sidebar-layout":{"type":"story","id":"common-twixtskeleton--left-sidebar-layout","name":"Left Sidebar Layout","title":"Common/TwixtSkeleton","importPath":"./stories/Skeleton.stories.js","tags":["autodocs","story"]},"common-twixtskeleton--right-sidebar-layout":{"type":"story","id":"common-twixtskeleton--right-sidebar-layout","name":"Right Sidebar Layout","title":"Common/TwixtSkeleton","importPath":"./stories/Skeleton.stories.js","tags":["autodocs","story"]},"common-twixtstats--docs":{"id":"common-twixtstats--docs","title":"Common/TwixtStats ","name":"Docs","importPath":"./stories/Stats.stories.js","type":"docs","tags":["autodocs","docs"],"storiesImports":[]},"common-twixtstats--default-stats":{"type":"story","id":"common-twixtstats--default-stats","name":"Default Stats","title":"Common/TwixtStats ","importPath":"./stories/Stats.stories.js","tags":["autodocs","story"]},"common-twixtswitch--docs":{"id":"common-twixtswitch--docs","title":"Common/TwixtSwitch","name":"Docs","importPath":"./stories/Switch.stories.js","type":"docs","tags":["autodocs","docs"],"storiesImports":[]},"common-twixtswitch--default":{"type":"story","id":"common-twixtswitch--default","name":"Default","title":"Common/TwixtSwitch","importPath":"./stories/Switch.stories.js","tags":["autodocs","story"]},"common-twixtswitch--show-password":{"type":"story","id":"common-twixtswitch--show-password","name":"Show Password","title":"Common/TwixtSwitch","importPath":"./stories/Switch.stories.js","tags":["autodocs","story"]}}}
